README.md
get-pip.py
setup.py
GloboNetworkAPI.egg-info/PKG-INFO
GloboNetworkAPI.egg-info/SOURCES.txt
GloboNetworkAPI.egg-info/dependency_links.txt
GloboNetworkAPI.egg-info/requires.txt
GloboNetworkAPI.egg-info/top_level.txt
networkapiclient/Ambiente.py
networkapiclient/AmbienteLogico.py
networkapiclient/ApiCIDREnvironment.py
networkapiclient/ApiEnvironment.py
networkapiclient/ApiEnvironmentDC.py
networkapiclient/ApiEnvironmentL3.py
networkapiclient/ApiEnvironmentLogic.py
networkapiclient/ApiEnvironmentVip.py
networkapiclient/ApiEquipment.py
networkapiclient/ApiGenericClient.py
networkapiclient/ApiIPv4.py
networkapiclient/ApiIPv6.py
networkapiclient/ApiInterface.py
networkapiclient/ApiNetworkIPv4.py
networkapiclient/ApiNetworkIPv6.py
networkapiclient/ApiObjectGroupPermission.py
networkapiclient/ApiObjectGroupPermissionGeneral.py
networkapiclient/ApiObjectType.py
networkapiclient/ApiOptionVip.py
networkapiclient/ApiPool.py
networkapiclient/ApiPoolDeploy.py
networkapiclient/ApiRack.py
networkapiclient/ApiV4As.py
networkapiclient/ApiV4Equipment.py
networkapiclient/ApiV4IPv4.py
networkapiclient/ApiV4IPv6.py
networkapiclient/ApiV4Neighbor.py
networkapiclient/ApiV4VirtualInterface.py
networkapiclient/ApiVipRequest.py
networkapiclient/ApiVlan.py
networkapiclient/ApiVrf.py
networkapiclient/BlockRule.py
networkapiclient/ClientFactory.py
networkapiclient/Config.py
networkapiclient/DireitoGrupoEquipamento.py
networkapiclient/DivisaoDc.py
networkapiclient/EnvironmentVIP.py
networkapiclient/Equipamento.py
networkapiclient/EquipamentoAcesso.py
networkapiclient/EquipamentoAmbiente.py
networkapiclient/EquipamentoRoteiro.py
networkapiclient/EspecificacaoGrupoVirtual.py
networkapiclient/EventLog.py
networkapiclient/Filter.py
networkapiclient/GenericClient.py
networkapiclient/GrupoEquipamento.py
networkapiclient/GrupoL3.py
networkapiclient/GrupoUsuario.py
networkapiclient/GrupoVirtual.py
networkapiclient/Healthcheck.py
networkapiclient/Interface.py
networkapiclient/Ip.py
networkapiclient/Marca.py
networkapiclient/Modelo.py
networkapiclient/Network.py
networkapiclient/OptionPool.py
networkapiclient/OptionVIP.py
networkapiclient/Pagination.py
