Metadata-Version: 1.0
Name: GloboNetworkAPI
Version: 0.9.3
Summary: GloboNetworkAPI Client Python
Home-page: https://github.com/globocom/GloboNetworkAPI-client-python
Author: Marcus Vinicius Gonçalves Cesário
Author-email: marcus.vinicius@corp.globo.com
License: LICENSE.txt
Keywords: network GloboNetwork GloboNetworkAPI
Platform: UNKNOWN
